atari/__init__.py
atari/cli.py
atari/core.py
atari/setup.py
atari/utils.py
atari/visualize.py
atari-0.1.4.dist-info/licenses/LICENSE
atari-0.1.4.dist-info/METADATA
atari-0.1.4.dist-info/WHEEL
atari-0.1.4.dist-info/entry_points.txt
atari-0.1.4.dist-info/top_level.txt
atari-0.1.4.dist-info/RECORD
