Metadata-Version: 2.4
Name: atari
Version: 0.1.4
Summary: AlternaTe Allele Read vIsualizer - A tool for analyzing genomic data from BAM files
Author-email: Samarth Mathur <samarth8392@gmail.com>
License: MIT
Project-URL: Homepage, https://github.com/samarth8392/atari
Project-URL: Bug Tracker, https://github.com/samarth8392/atari/issues
Classifier: Programming Language :: Python :: 3
Classifier: License :: OSI Approved :: MIT License
Classifier: Operating System :: OS Independent
Classifier: Topic :: Scientific/Engineering :: Bio-Informatics
Requires-Python: >=3.7
License-File: LICENSE
Requires-Dist: pandas
Requires-Dist: pysam
Requires-Dist: matplotlib
Requires-Dist: numpy
Requires-Dist: tqdm
Requires-Dist: rich
Dynamic: license-file
